throttler/__init__.py
throttler/decorators.py
throttler/execution_timer.py
throttler/throttler.py
throttler/throttler_simultaneous.py
throttler/timer.py
throttler-1.2.2.dist-info/LICENSE
throttler-1.2.2.dist-info/METADATA
throttler-1.2.2.dist-info/WHEEL
throttler-1.2.2.dist-info/top_level.txt
throttler-1.2.2.dist-info/RECORD
