Metadata-Version: 2.1
Name: throttler
Version: 1.2.2
Summary: Zero-dependency Python package for easy throttling with asyncio support
Home-page: https://github.com/uburuntu/throttler
Download-URL: https://github.com/uburuntu/throttler/archive/master.zip
Author: uburuntu
Author-email: github@rmbk.me
License: MIT
Keywords: asyncio,aio-throttle,aiothrottle,aiothrottler,aiothrottling,asyncio-throttle,rate-limit,rate-limiter,throttling,throttle,throttler
Platform: all
Classifier: Development Status :: 5 - Production/Stable
Classifier: Framework :: AsyncIO
Classifier: Intended Audience :: Developers
Classifier: Intended Audience :: System Administrators
Classifier: License :: OSI Approved :: MIT License
Classifier: Programming Language :: Python :: 3
Classifier: Typing :: Typed
Provides-Extra: dev
License-File: LICENSE
